<?xml version="1.0" encoding="utf-8"?>
<DownloadBPDataResultEntity xmlns:xsd="http://www.w3.org/2001/XMLSchema" xmlns:xsi="http://www.w3.org/2001/XMLSchema-instance">
    <BPDataList>
        <DownloadBPDataEntity>
            <userid>87a370062ace417e892d81254344eaf3</userid>
            <BPL>5</BPL>
            <DataID>23fc4eb8d8e886b0ea70d91ccbcd7137</DataID>
            <HP>122</HP>
            <HR>57</HR>
            <IsArr>0</IsArr>
            <Lat>0</Lat>
            <Lon>0</Lon>
            <LP>82</LP>
            <MDate>1478692812</MDate>
            <Note>First test</Note>
            <LastChangeTime>1478655047</LastChangeTime>
            <DataSource>FromDevice</DataSource>
            <TimeZone>+1050</TimeZone>
        </DownloadBPDataEntity>
        <DownloadBPDataEntity>
            <userid>87a370062ace417e892d81254344eaf3</userid>
            <BPL>5</BPL>
            <DataID>d5b101eaddf2c0600e60b569d89012db</DataID>
            <HP>122</HP>
            <HR>70</HR>
            <IsArr>0</IsArr>
            <Lat>0</Lat>
            <Lon>0</Lon>
            <LP>77</LP>
            <MDate>1478697310</MDate>
            <Note>after lunch</Note>
            <LastChangeTime>1478659529</LastChangeTime>
            <DataSource>FromDevice</DataSource>
            <TimeZone>+1050</TimeZone>
        </DownloadBPDataEntity>
        <DownloadBPDataEntity>
            <userid>87a370062ace417e892d81254344eaf3</userid>
            <BPL>2</BPL>
            <DataID>a26696dadf220c93551341c5c5130676</DataID>
            <HP>152</HP>
            <HR>108</HR>
            <IsArr>0</IsArr>
            <Lat>0</Lat>
            <Lon>0</Lon>
            <LP>102</LP>
            <MDate>1478697421</MDate>
            <Note>tensing</Note>
            <LastChangeTime>1478659643</LastChangeTime>
            <DataSource>FromDevice</DataSource>
            <TimeZone>+1050</TimeZone>
        </DownloadBPDataEntity>
        <DownloadBPDataEntity>
            <userid>87a370062ace417e892d81254344eaf3</userid>
            <BPL>2</BPL>
            <DataID>56e9a9be67f10d7efb4d1fc6b48496f7</DataID>
            <HP>127</HP>
            <HR>71</HR>
            <IsArr>0</IsArr>
            <Lat>0</Lat>
            <Lon>0</Lon>
            <LP>100</LP>
            <MDate>1478700868</MDate>
            <Note>Trump winning</Note>
            <LastChangeTime>1478663119</LastChangeTime>
            <DataSource>FromDevice</DataSource>
            <TimeZone>+1050</TimeZone>
        </DownloadBPDataEntity>
        <DownloadBPDataEntity>
            <userid>87a370062ace417e892d81254344eaf3</userid>
            <BPL>3</BPL>
            <DataID>82560a9a9cef386c91faaff99f2f0855</DataID>
            <HP>132</HP>
            <HR>71</HR>
            <IsArr>0</IsArr>
            <Lat>0</Lat>
            <Lon>0</Lon>
            <LP>90</LP>
            <MDate>1478703526</MDate>
            <Note>he's won</Note>
            <LastChangeTime>1478665740</LastChangeTime>
            <DataSource>FromDevice</DataSource>
            <TimeZone>+1050</TimeZone>
        </DownloadBPDataEntity>
        <DownloadBPDataEntity>
            <userid>87a370062ace417e892d81254344eaf3</userid>
            <BPL>3</BPL>
            <DataID>0dcfcd514996810e0b29f61c11e215a8</DataID>
            <HP>130</HP>
            <HR>73</HR>
            <IsArr>0</IsArr>
            <Lat>0</Lat>
            <Lon>0</Lon>
            <LP>90</LP>
            <MDate>1478703604</MDate>
            <Note>again</Note>
            <LastChangeTime>1478665821</LastChangeTime>
            <DataSource>FromDevice</DataSource>
            <TimeZone>+1050</TimeZone>
        </DownloadBPDataEntity>
        <DownloadBPDataEntity>
            <userid>87a370062ace417e892d81254344eaf3</userid>
            <BPL>4</BPL>
            <DataID>911dd5591362fefdf02a14a7bf7d479a</DataID>
            <HP>133</HP>
            <HR>68</HR>
            <IsArr>0</IsArr>
            <Lat>0</Lat>
            <Lon>0</Lon>
            <LP>86</LP>
            <MDate>1478765244</MDate>
            <Note />
            <LastChangeTime>1478727460</LastChangeTime>
            <DataSource>FromDevice</DataSource>
            <TimeZone>+1050</TimeZone>
        </DownloadBPDataEntity>
        <DownloadBPDataEntity>
            <userid>87a370062ace417e892d81254344eaf3</userid>
            <BPL>6</BPL>
            <DataID>8fb7a6e17570d5094ad90464a4ff3eca</DataID>
            <HP>112</HP>
            <HR>60</HR>
            <IsArr>0</IsArr>
            <Lat>0</Lat>
            <Lon>0</Lon>
            <LP>77</LP>
            <MDate>1478773323</MDate>
            <Note />
            <LastChangeTime>1478735537</LastChangeTime>
            <DataSource>FromDevice</DataSource>
            <TimeZone>+1050</TimeZone>
        </DownloadBPDataEntity>
        <DownloadBPDataEntity>
            <userid>87a370062ace417e892d81254344eaf3</userid>
            <BPL>4</BPL>
            <DataID>b43775ff6d70bc6d8872c8592ba4b334</DataID>
            <HP>132</HP>
            <HR>75</HR>
            <IsArr>0</IsArr>
            <Lat>0</Lat>
            <Lon>0</Lon>
            <LP>89</LP>
            <MDate>1478787582</MDate>
            <Note>after lunch</Note>
            <LastChangeTime>1478749797</LastChangeTime>
            <DataSource>FromDevice</DataSource>
            <TimeZone>+1050</TimeZone>
        </DownloadBPDataEntity>
        <DownloadBPDataEntity>
            <userid>87a370062ace417e892d81254344eaf3</userid>
            <BPL>4</BPL>
            <DataID>b1cb0ac46b5c64b72b0d2d57c4f02bd6</DataID>
            <HP>137</HP>
            <HR>62</HR>
            <IsArr>0</IsArr>
            <Lat>0</Lat>
            <Lon>0</Lon>
            <LP>83</LP>
            <MDate>1478793398</MDate>
            <Note>testing</Note>
            <LastChangeTime>1478755643</LastChangeTime>
            <DataSource>FromDevice</DataSource>
            <TimeZone>+1050</TimeZone>
        </DownloadBPDataEntity>
        <DownloadBPDataEntity>
            <userid>87a370062ace417e892d81254344eaf3</userid>
            <BPL>3</BPL>
            <DataID>91eb1dc26139250ef956d6e9f8e73e5b</DataID>
            <HP>141</HP>
            <HR>73</HR>
            <IsArr>0</IsArr>
            <Lat>0</Lat>
            <Lon>0</Lon>
            <LP>78</LP>
            <MDate>1478853128</MDate>
            <Note />
            <LastChangeTime>1478815347</LastChangeTime>
            <DataSource>FromDevice</DataSource>
            <TimeZone>+1050</TimeZone>
        </DownloadBPDataEntity>
        <DownloadBPDataEntity>
            <userid>87a370062ace417e892d81254344eaf3</userid>
            <BPL>3</BPL>
            <DataID>b646abc0f20a22981c55c6ad51354070</DataID>
            <HP>142</HP>
            <HR>73</HR>
            <IsArr>0</IsArr>
            <Lat>0</Lat>
            <Lon>0</Lon>
            <LP>71</LP>
            <MDate>1478853206</MDate>
            <Note>repeated Reading</Note>
            <LastChangeTime>1478815423</LastChangeTime>
            <DataSource>FromDevice</DataSource>
            <TimeZone>+1050</TimeZone>
        </DownloadBPDataEntity>
        <DownloadBPDataEntity>
            <userid>87a370062ace417e892d81254344eaf3</userid>
            <BPL>4</BPL>
            <DataID>169da6d6dfc8932d100b6a89835ca586</DataID>
            <HP>139</HP>
            <HR>67</HR>
            <IsArr>0</IsArr>
            <Lat>0</Lat>
            <Lon>0</Lon>
            <LP>72</LP>
            <MDate>1478858340</MDate>
            <Note />
            <LastChangeTime>1478820540</LastChangeTime>
            <DataSource>FromDevice</DataSource>
            <TimeZone>+1050</TimeZone>
        </DownloadBPDataEntity>
        <DownloadBPDataEntity>
            <userid>87a370062ace417e892d81254344eaf3</userid>
            <BPL>3</BPL>
            <DataID>115b17a7f373a9800a81929cacdbceb3</DataID>
            <HP>145</HP>
            <HR>72</HR>
            <IsArr>0</IsArr>
            <Lat>0</Lat>
            <Lon>0</Lon>
            <LP>71</LP>
            <MDate>1478858483</MDate>
            <Note>testing</Note>
            <LastChangeTime>1478820699</LastChangeTime>
            <DataSource>FromDevice</DataSource>
            <TimeZone>+1050</TimeZone>
        </DownloadBPDataEntity>
        <DownloadBPDataEntity>
            <userid>87a370062ace417e892d81254344eaf3</userid>
            <BPL>4</BPL>
            <DataID>bf2be0f05926b91e5254d79d8837c650</DataID>
            <HP>137</HP>
            <HR>63</HR>
            <IsArr>0</IsArr>
            <Lat>0</Lat>
            <Lon>0</Lon>
            <LP>84</LP>
            <MDate>1478859305</MDate>
            <Note />
            <LastChangeTime>1478821524</LastChangeTime>
            <DataSource>FromDevice</DataSource>
            <TimeZone>+1050</TimeZone>
        </DownloadBPDataEntity>
        <DownloadBPDataEntity>
            <userid>87a370062ace417e892d81254344eaf3</userid>
            <BPL>5</BPL>
            <DataID>609d6b0e982799840019f62c2ed0a86c</DataID>
            <HP>122</HP>
            <HR>76</HR>
            <IsArr>0</IsArr>
            <Lat>0</Lat>
            <Lon>0</Lon>
            <LP>82</LP>
            <MDate>1478871911</MDate>
            <Note>after lunch</Note>
            <LastChangeTime>1478834126</LastChangeTime>
            <DataSource>FromDevice</DataSource>
            <TimeZone>+1050</TimeZone>
        </DownloadBPDataEntity>
        <DownloadBPDataEntity>
            <userid>87a370062ace417e892d81254344eaf3</userid>
            <BPL>5</BPL>
            <DataID>ebe649929e4034e004d48373feb3cdfc</DataID>
            <HP>122</HP>
            <HR>72</HR>
            <IsArr>0</IsArr>
            <Lat>0</Lat>
            <Lon>0</Lon>
            <LP>81</LP>
            <MDate>1478871976</MDate>
            <Note>Quick repeat to validate</Note>
            <LastChangeTime>1478834197</LastChangeTime>
            <DataSource>FromDevice</DataSource>
            <TimeZone>+1050</TimeZone>
        </DownloadBPDataEntity>
        <DownloadBPDataEntity>
            <userid>87a370062ace417e892d81254344eaf3</userid>
            <BPL>4</BPL>
            <DataID>e9d33973c33ff779e67cba6ff0d104fe</DataID>
            <HP>138</HP>
            <HR>66</HR>
            <IsArr>0</IsArr>
            <Lat>0</Lat>
            <Lon>0</Lon>
            <LP>85</LP>
            <MDate>1479065042</MDate>
            <Note>rating</Note>
            <LastChangeTime>1479027265</LastChangeTime>
            <DataSource>FromDevice</DataSource>
            <TimeZone>+1050</TimeZone>
        </DownloadBPDataEntity>
        <DownloadBPDataEntity>
            <userid>87a370062ace417e892d81254344eaf3</userid>
            <BPL>6</BPL>
            <DataID>b3d907ed3d5319fe39bb02eee5ad273d</DataID>
            <HP>108</HP>
            <HR>66</HR>
            <IsArr>0</IsArr>
            <Lat>0</Lat>
            <Lon>0</Lon>
            <LP>68</LP>
            <MDate>1479065110</MDate>
            <Note />
            <LastChangeTime>1479027310</LastChangeTime>
            <DataSource>FromDevice</DataSource>
            <TimeZone>+1050</TimeZone>
        </DownloadBPDataEntity>
        <DownloadBPDataEntity>
            <userid>87a370062ace417e892d81254344eaf3</userid>
            <BPL>1</BPL>
            <DataID>e3fb03a878451e7711cd67dfb8fb7d48</DataID>
            <HP>155</HP>
            <HR>76</HR>
            <IsArr>0</IsArr>
            <Lat>0</Lat>
            <Lon>0</Lon>
            <LP>113</LP>
            <MDate>1479065225</MDate>
            <Note />
            <LastChangeTime>1479027425</LastChangeTime>
            <DataSource>FromDevice</DataSource>
            <TimeZone>+1050</TimeZone>
        </DownloadBPDataEntity>
        <DownloadBPDataEntity>
            <userid>87a370062ace417e892d81254344eaf3</userid>
            <BPL>6</BPL>
            <DataID>18d10b3bc1b1f578c97214afe999c57a</DataID>
            <HP>118</HP>
            <HR>66</HR>
            <IsArr>0</IsArr>
            <Lat>0</Lat>
            <Lon>0</Lon>
            <LP>78</LP>
            <MDate>1479065318</MDate>
            <Note />
            <LastChangeTime>1479027518</LastChangeTime>
            <DataSource>FromDevice</DataSource>
            <TimeZone>+1050</TimeZone>
        </DownloadBPDataEntity>
        <DownloadBPDataEntity>
            <userid>87a370062ace417e892d81254344eaf3</userid>
            <BPL>6</BPL>
            <DataID>28adb42ea33cd4040b075d216db81efa</DataID>
            <HP>117</HP>
            <HR>73</HR>
            <IsArr>0</IsArr>
            <Lat>0</Lat>
            <Lon>0</Lon>
            <LP>59</LP>
            <MDate>1479065484</MDate>
            <Note />
            <LastChangeTime>1479027684</LastChangeTime>
            <DataSource>FromDevice</DataSource>
            <TimeZone>+1050</TimeZone>
        </DownloadBPDataEntity>
        <DownloadBPDataEntity>
            <userid>87a370062ace417e892d81254344eaf3</userid>
            <BPL>3</BPL>
            <DataID>beeda71d4d01c67bf991e9a88f2273fd</DataID>
            <HP>142</HP>
            <HR>70</HR>
            <IsArr>0</IsArr>
            <Lat>0</Lat>
            <Lon>0</Lon>
            <LP>78</LP>
            <MDate>1479116318</MDate>
            <Note />
            <LastChangeTime>1479078527</LastChangeTime>
            <DataSource>FromDevice</DataSource>
            <TimeZone>+1050</TimeZone>
        </DownloadBPDataEntity>
        <DownloadBPDataEntity>
            <userid>87a370062ace417e892d81254344eaf3</userid>
            <BPL>5</BPL>
            <DataID>594005de6f40e20e68714c9f69ec7553</DataID>
            <HP>124</HP>
            <HR>62</HR>
            <IsArr>0</IsArr>
            <Lat>0</Lat>
            <Lon>0</Lon>
            <LP>77</LP>
            <MDate>1479134183</MDate>
            <Note />
            <LastChangeTime>1479096393</LastChangeTime>
            <DataSource>FromDevice</DataSource>
            <TimeZone>+1050</TimeZone>
        </DownloadBPDataEntity>
        <DownloadBPDataEntity>
            <userid>87a370062ace417e892d81254344eaf3</userid>
            <BPL>3</BPL>
            <DataID>26515d8ab0cbb9ea02ea43b8629575d2</DataID>
            <HP>123</HP>
            <HR>78</HR>
            <IsArr>0</IsArr>
            <Lat>0</Lat>
            <Lon>0</Lon>
            <LP>97</LP>
            <MDate>1479203257</MDate>
            <Note>travel anxiety</Note>
            <LastChangeTime>1479165469</LastChangeTime>
            <DataSource>FromDevice</DataSource>
            <TimeZone>+1050</TimeZone>
        </DownloadBPDataEntity>
        <DownloadBPDataEntity>
            <userid>87a370062ace417e892d81254344eaf3</userid>
            <BPL>4</BPL>
            <DataID>e1a50a1de1862ee44c094e1408ef7f7a</DataID>
            <HP>132</HP>
            <HR>79</HR>
            <IsArr>0</IsArr>
            <Lat>0</Lat>
            <Lon>0</Lon>
            <LP>85</LP>
            <MDate>1479226015</MDate>
            <Note>got iot activation working</Note>
            <LastChangeTime>1479188231</LastChangeTime>
            <DataSource>FromDevice</DataSource>
            <TimeZone>+1050</TimeZone>
        </DownloadBPDataEntity>
        <DownloadBPDataEntity>
            <userid>87a370062ace417e892d81254344eaf3</userid>
            <BPL>4</BPL>
            <DataID>ef80d5d914a593f102bddd1c1b0a68f5</DataID>
            <HP>121</HP>
            <HR>96</HR>
            <IsArr>0</IsArr>
            <Lat>0</Lat>
            <Lon>0</Lon>
            <LP>85</LP>
            <MDate>1479306997</MDate>
            <Note />
            <LastChangeTime>1479269197</LastChangeTime>
            <DataSource>FromDevice</DataSource>
            <TimeZone>+1050</TimeZone>
        </DownloadBPDataEntity>
        <DownloadBPDataEntity>
            <userid>87a370062ace417e892d81254344eaf3</userid>
            <BPL>1</BPL>
            <DataID>662180d14cc9a10a676e8d6b532ea977</DataID>
            <HP>129</HP>
            <HR>65</HR>
            <IsArr>0</IsArr>
            <Lat>0</Lat>
            <Lon>0</Lon>
            <LP>119</LP>
            <MDate>1479472440</MDate>
            <Note />
            <LastChangeTime>1479434640</LastChangeTime>
            <DataSource>FromDevice</DataSource>
            <TimeZone>+1050</TimeZone>
        </DownloadBPDataEntity>
        <DownloadBPDataEntity>
            <userid>87a370062ace417e892d81254344eaf3</userid>
            <BPL>2</BPL>
            <DataID>bbe3adfac8e6a1cfeb67a5b3bc473d61</DataID>
            <HP>131</HP>
            <HR>65</HR>
            <IsArr>0</IsArr>
            <Lat>0</Lat>
            <Lon>0</Lon>
            <LP>101</LP>
            <MDate>1479472860</MDate>
            <Note />
            <LastChangeTime>1479435060</LastChangeTime>
            <DataSource>FromDevice</DataSource>
            <TimeZone>+1050</TimeZone>
        </DownloadBPDataEntity>
        <DownloadBPDataEntity>
            <userid>87a370062ace417e892d81254344eaf3</userid>
            <BPL>3</BPL>
            <DataID>1b49947ff2d600302cbc2261539c52b6</DataID>
            <HP>132</HP>
            <HR>66</HR>
            <IsArr>0</IsArr>
            <Lat>0</Lat>
            <Lon>0</Lon>
            <LP>93</LP>
            <MDate>1479473460</MDate>
            <Note />
            <LastChangeTime>1479435660</LastChangeTime>
            <DataSource>FromDevice</DataSource>
            <TimeZone>+1050</TimeZone>
        </DownloadBPDataEntity>
        <DownloadBPDataEntity>
            <userid>87a370062ace417e892d81254344eaf3</userid>
            <BPL>3</BPL>
            <DataID>b96b95cf14fc310089f34d5e964a4345</DataID>
            <HP>134</HP>
            <HR>65</HR>
            <IsArr>0</IsArr>
            <Lat>0</Lat>
            <Lon>0</Lon>
            <LP>95</LP>
            <MDate>1479474600</MDate>
            <Note />
            <LastChangeTime>1479436800</LastChangeTime>
            <DataSource>FromDevice</DataSource>
            <TimeZone>+1050</TimeZone>
        </DownloadBPDataEntity>
        <DownloadBPDataEntity>
            <userid>87a370062ace417e892d81254344eaf3</userid>
            <BPL>4</BPL>
            <DataID>6ea3566c89f43b9248134f8431e0885e</DataID>
            <HP>128</HP>
            <HR>59</HR>
            <IsArr>0</IsArr>
            <Lat>0</Lat>
            <Lon>0</Lon>
            <LP>87</LP>
            <MDate>1479729616</MDate>
            <Note>working</Note>
            <LastChangeTime>1479691838</LastChangeTime>
            <DataSource>FromDevice</DataSource>
            <TimeZone>+1050</TimeZone>
        </DownloadBPDataEntity>
        <DownloadBPDataEntity>
            <userid>87a370062ace417e892d81254344eaf3</userid>
            <BPL>5</BPL>
            <DataID>fa91a7f5a9a2ecb2ea652fa66468e412</DataID>
            <HP>120</HP>
            <HR>60</HR>
            <IsArr>0</IsArr>
            <Lat>0</Lat>
            <Lon>0</Lon>
            <LP>80</LP>
            <MDate>1479737841</MDate>
            <Note>manual entry sunil</Note>
            <LastChangeTime>1479698290</LastChangeTime>
            <DataSource>Manual</DataSource>
            <TimeZone>+1100</TimeZone>
        </DownloadBPDataEntity>
        <DownloadBPDataEntity>
            <userid>87a370062ace417e892d81254344eaf3</userid>
            <BPL>3</BPL>
            <DataID>c2a1331e0f8cff81551a360e714014f4</DataID>
            <HP>128</HP>
            <HR>45</HR>
            <IsArr>0</IsArr>
            <Lat>0</Lat>
            <Lon>0</Lon>
            <LP>92</LP>
            <MDate>1479828467</MDate>
            <Note />
            <LastChangeTime>1479790909</LastChangeTime>
            <DataSource>FromDevice</DataSource>
            <TimeZone>+1050</TimeZone>
        </DownloadBPDataEntity>
        <DownloadBPDataEntity>
            <userid>87a370062ace417e892d81254344eaf3</userid>
            <BPL>3</BPL>
            <DataID>4e3b56b16d8af066d99d740d6cf528fa</DataID>
            <HP>129</HP>
            <HR>69</HR>
            <IsArr>0</IsArr>
            <Lat>0</Lat>
            <Lon>0</Lon>
            <LP>90</LP>
            <MDate>1479996593</MDate>
            <Note>eclipse crashing along with everything else</Note>
            <LastChangeTime>1479958825</LastChangeTime>
            <DataSource>FromDevice</DataSource>
            <TimeZone>+1050</TimeZone>
        </DownloadBPDataEntity>
        <DownloadBPDataEntity>
            <userid>87a370062ace417e892d81254344eaf3</userid>
            <BPL>3</BPL>
            <DataID>dc33b2a5751473227f22813c9cb40fa9</DataID>
            <HP>130</HP>
            <HR>61</HR>
            <IsArr>0</IsArr>
            <Lat>0</Lat>
            <Lon>0</Lon>
            <LP>95</LP>
            <MDate>1480072907</MDate>
            <Note />
            <LastChangeTime>1480035113</LastChangeTime>
            <DataSource>FromDevice</DataSource>
            <TimeZone>+1050</TimeZone>
        </DownloadBPDataEntity>
    </BPDataList>
    <BPUnit>0</BPUnit>
    <CurrentRecordCount>36</CurrentRecordCount>
    <NextPageUrl />
    <PageLength>50</PageLength>
    <PageNumber>1</PageNumber>
    <PrevPageUrl />
    <RecordCount>36</RecordCount>
</DownloadBPDataResultEntity>